abs_sleep/__init__.py
abs_sleep/py.typed
abs_sleep-1.0.0.dist-info/METADATA
abs_sleep-1.0.0.dist-info/WHEEL
abs_sleep-1.0.0.dist-info/licenses/LICENSE
abs_sleep-1.0.0.dist-info/RECORD
